smallevals/__init__.py
smallevals/api.py
smallevals/cli.py
smallevals/exceptions.py
smallevals/eval/__init__.py
smallevals/eval/engine.py
smallevals/eval/metrics.py
smallevals/eval/analysis/__init__.py
smallevals/eval/analysis/failure_analysis.py
smallevals/eval/analysis/retrieval_patterns.py
smallevals/eval/analysis/text_structure.py
smallevals/generation/__init__.py
smallevals/generation/qa_generator.py
smallevals/logo/smallevals_emoji_128_128.png
smallevals/logo/smallevals_emoji_32_32.png
smallevals/logo/smallevals_emoji_64_64.png
smallevals/models/__init__.py
smallevals/models/golden_generator.py
smallevals/ui_dash/__init__.py
smallevals/ui_dash/app.py
smallevals/ui_dash/callbacks.py
smallevals/ui_dash/components.py
smallevals/ui_dash/ranking.py
smallevals/ui_dash/report_generator.py
smallevals/utils/__init__.py
smallevals/utils/data_organization.py
smallevals/utils/json_parser.py
smallevals/utils/logger.py
smallevals/utils/results_manager.py
smallevals/utils/versioning.py
smallevals/vdb_integrations/__init__.py
smallevals/vdb_integrations/base.py
smallevals/vdb_integrations/chroma_con.py
smallevals/vdb_integrations/connection.py
smallevals/vdb_integrations/elastic_con.py
smallevals/vdb_integrations/faiss_con.py
smallevals/vdb_integrations/milvus_con.py
smallevals/vdb_integrations/mongodb_con.py
smallevals/vdb_integrations/pgvector_con.py
smallevals/vdb_integrations/pinecone_con.py
smallevals/vdb_integrations/qdrant_con.py
smallevals/vdb_integrations/turbopuffer_con.py
smallevals/vdb_integrations/utils.py
smallevals/vdb_integrations/weaviate_con.py
smallevals/vectordb/__init__.py
smallevals-0.1.8.dist-info/licenses/LICENSE
smallevals-0.1.8.dist-info/METADATA
smallevals-0.1.8.dist-info/WHEEL
smallevals-0.1.8.dist-info/entry_points.txt
smallevals-0.1.8.dist-info/top_level.txt
smallevals-0.1.8.dist-info/RECORD
