Metadata-Version: 2.4
Name: smallevals
Version: 0.1.8
Summary: Small Language Models Evaluation Suite for RAG Systems
Author-email: Mehmet Burak Sayıcı <mburaksayici@gmail.com>
License-Expression: MIT
Project-URL: Homepage, https://github.com/mburaksayici/smallevals
Project-URL: Repository, https://github.com/mburaksayici/smallevals
Project-URL: Issues, https://github.com/mburaksayici/smallevals/issues
Project-URL: Documentation, https://github.com/mburaksayici/smallevals#readme
Keywords: rag,evaluation,vector-database,retrieval,nlp,llm,small-language-models
Classifier: Development Status :: 3 - Alpha
Classifier: Intended Audience :: Developers
Classifier: Intended Audience :: Science/Research
Classifier: Programming Language :: Python :: 3
Classifier: Programming Language :: Python :: 3.10
Classifier: Programming Language :: Python :: 3.11
Classifier: Programming Language :: Python :: 3.12
Classifier: Topic :: Software Development :: Libraries :: Python Modules
Classifier: Topic :: Scientific/Engineering :: Artificial Intelligence
Requires-Python: >=3.10
License-File: LICENSE
Requires-Dist: openai>=2.8.1
Requires-Dist: python-dotenv>=1.2.1
Requires-Dist: tqdm>=4.67.1
Requires-Dist: sentence-transformers>=5.1.2
Requires-Dist: pandas>=2.0.0
Requires-Dist: peft>=0.18.0
Requires-Dist: docling>=2.60.0
Requires-Dist: nltk>=3.8
Requires-Dist: numpy<2.3,>=2
Requires-Dist: transformers>=4.30.0; sys_platform == "win32"
Requires-Dist: hf-transfer>=0.1.9; sys_platform == "win32"
Requires-Dist: torch>=2.0.0; sys_platform == "win32"
Requires-Dist: llama-cpp-python>=0.3.16; sys_platform == "darwin" or sys_platform == "linux"
Requires-Dist: plotly>=5.0.0
Requires-Dist: dash>=2.14.0
Requires-Dist: dash-bootstrap-components>=1.5.0
Requires-Dist: chromadb>=1.3.5
Requires-Dist: weaviate-client>=4.18.1
Requires-Dist: faiss-cpu>=1.13.0
Requires-Dist: pinecone-client>=3.0.0
Requires-Dist: pymilvus>=2.6.3
Requires-Dist: elasticsearch>=8.11
Requires-Dist: elastic-transport>=8.11
Requires-Dist: psycopg2-binary>=2.9.11
Requires-Dist: sqlalchemy>=2.0.0
Requires-Dist: qdrant-client>=1.16.1
Requires-Dist: pymongo>=4.0.0
Requires-Dist: turbopuffer>=0.1.0
Provides-Extra: test
Requires-Dist: pytest>=9.0.1; extra == "test"
Requires-Dist: pytest-cov>=4.0.0; extra == "test"
Requires-Dist: testcontainers[elasticsearch,weaviate]>=4.13.3; extra == "test"
Requires-Dist: pyarrow>=10.0.0; extra == "test"
Dynamic: license-file
